LICENSE.md
MANIFEST.in
README.md
setup.cfg
setup.py
rollastic/__init__.py
rollastic/__main__.py
rollastic/_version.py
rollastic/cluster.py
rollastic/config.py
rollastic/log.py
rollastic/node.py
rollastic.egg-info/PKG-INFO
rollastic.egg-info/SOURCES.txt
rollastic.egg-info/dependency_links.txt
rollastic.egg-info/entry_points.txt
rollastic.egg-info/requires.txt
rollastic.egg-info/top_level.txt