Metadata-Version: 1.1
Name: rollastic
Version: 0.0.7
Summary: Automated ElasticSearch cluster rolling restarts/upgrades via SaltStack
Home-page: http://github.com/vertical-knowledge/rollastic
Author: VK
Author-email: vk@vertical-knowledge.com
License: GPL
Download-URL: http://github.com/vertical-knowledge/rollastic/tarball/0.0.7
Keywords: elasticsearch,elastic,cluster,salt,saltstack,rolling,upgrade,restart
Platform: UNKNOWN
